nfeloml/__init__.py
nfeloml/core/__init__.py
nfeloml/core/base_data_loader.py
nfeloml/core/base_model.py
nfeloml/core/base_trainer.py
nfeloml/core/types.py
nfeloml/models/__init__.py
nfeloml/models/expected_points/__init__.py
nfeloml/models/expected_points/data_loader.py
nfeloml/models/expected_points/model.py
nfeloml/models/expected_points/trainer.py
nfeloml/models/expected_points/types.py
nfeloml/models/expected_points/trained_model/metadata.json
nfeloml/models/expected_points/trained_model/model.ubj
nfeloml/models/expected_points/utils/__init__.py
nfeloml/models/expected_points/utils/features.py
nfeloml/models/expected_points/utils/next_score.py
nfeloml/models/win_probability/__init__.py
nfeloml/models/win_probability/data_loader.py
nfeloml/models/win_probability/model.py
nfeloml/models/win_probability/trainer.py
nfeloml/models/win_probability/types.py
nfeloml/models/win_probability/trained_model/metadata.json
nfeloml/models/win_probability/trained_model/model.ubj
nfeloml/utils/__init__.py
nfeloml/utils/epa.py
nfeloml/utils/validation.py
nfeloml-0.1.11.dist-info/METADATA
nfeloml-0.1.11.dist-info/WHEEL
nfeloml-0.1.11.dist-info/top_level.txt
nfeloml-0.1.11.dist-info/RECORD
