Metadata-Version: 2.4
Name: nfeloml
Version: 0.1.11
Summary: Portable machine learning models for NFL analytics
Author-email: Robert Greer <greerreNFL@users.noreply.github.com>
License: MIT
Project-URL: Homepage, https://github.com/greerreNFL/nfeloml
Project-URL: Repository, https://github.com/greerreNFL/nfeloml
Project-URL: Issues, https://github.com/greerreNFL/nfeloml/issues
Keywords: nfl,analytics
Requires-Python: >=3.9
Requires-Dist: xgboost>=2.0.0
Requires-Dist: pandas>=2.0.0
Requires-Dist: numpy>=1.24.0
Provides-Extra: training
Requires-Dist: nfelodcm>=0.1.24; extra == "training"
